README.rst
YahooTickerDownloader.py
setup.py
Yahoo_ticker_downloader.egg-info/PKG-INFO
Yahoo_ticker_downloader.egg-info/SOURCES.txt
Yahoo_ticker_downloader.egg-info/dependency_links.txt
Yahoo_ticker_downloader.egg-info/requires.txt
Yahoo_ticker_downloader.egg-info/top_level.txt
ytd/SimpleSymbolDownloader.py
ytd/Symbol.py
ytd/__init__.py
ytd/compat.py
ytd/downloader/GenericDownloader.py
ytd/downloader/__init__.py
ytd/symbols/Generic.py
ytd/symbols/__init__.py