Metadata-Version: 1.1
Name: Yahoo-ticker-downloader
Version: 3.0.1
Summary: A web scraper for ticker symbols from yahoo finance
Home-page: https://github.com/Benny-/Yahoo-ticker-symbol-downloader
Author: Benny Jacobs
Author-email: Benny@GMX.it
License: BSD3
Keywords: market,finance,yahoo,ticker,stock,stocks,etf,future,futures,index,mutualfund,currency,warrant,bond,bonds
Platform: UNKNOWN
Classifier: Operating System :: OS Independent
Classifier: Programming Language :: Python
Classifier: Programming Language :: Python :: 2
Classifier: Programming Language :: Python :: 3
Classifier: Environment :: Console
Classifier: Topic :: Office/Business :: Financial :: Investment
Classifier: License :: OSI Approved :: BSD License
